<?xml version="1.0" encoding="UTF-8"?>
<GenRun Id="impl_1" LaunchPart="xc7z010clg400-1" LaunchTime="1487593994">
  <File Type="OPT-METHODOLOGY-DRC" Name="vivado_wrapper_methodology_drc_opted.rpt"/>
  <File Type="PLACE-CTRL" Name="vivado_wrapper_control_sets_placed.rpt"/>
  <File Type="OPT-TIMING" Name="vivado_wrapper_timing_summary_opted.rpt"/>
  <File Type="POSTPLACE-PWROPT-TIMING" Name="vivado_wrapper_timing_summary_postplace_pwropted.rpt"/>
  <File Type="PLACE-IO" Name="vivado_wrapper_io_placed.rpt"/>
  <File Type="POSTROUTE-PHYSOPT-DCP" Name="vivado_wrapper_postroute_physopt.dcp"/>
  <File Type="PA-TCL" Name="vivado_wrapper.tcl"/>
  <File Type="PHYSOPT-TIMING" Name="vivado_wrapper_timing_summary_physopted.rpt"/>
  <File Type="PLACE-CLK" Name="vivado_wrapper_clock_utilization_placed.rpt"/>
  <File Type="PLACE-UTIL" Name="vivado_wrapper_utilization_placed.rpt"/>
  <File Type="PLACE-UTIL-PB" Name="vivado_wrapper_utilization_placed.pb"/>
  <File Type="PWROPT-DRC" Name="vivado_wrapper_drc_pwropted.rpt"/>
  <File Type="BITSTR-SYSDEF" Name="vivado_wrapper.sysdef"/>
  <File Type="ROUTE-TIMING-RPX" Name="vivado_wrapper_timing_summary_routed.rpx"/>
  <File Type="BG-BGN" Name="vivado_wrapper.bgn"/>
  <File Type="POSTROUTE-PHYSOPT-TIMING-RPX" Name="vivado_wrapper_timing_summary_postroute_physopted.rpx"/>
  <File Type="BITSTR-MMI" Name="vivado_wrapper.mmi"/>
  <File Type="ROUTE-TIMING-PB" Name="vivado_wrapper_timing_summary_routed.pb"/>
  <File Type="BG-DRC" Name="vivado_wrapper.drc"/>
  <File Type="POSTROUTE-PHYSOPT-TIMING-PB" Name="vivado_wrapper_timing_summary_postroute_physopted.pb"/>
  <File Type="OPT-DRC" Name="vivado_wrapper_drc_opted.rpt"/>
  <File Type="PLACE-PRE-SIMILARITY" Name="vivado_wrapper_incremental_reuse_pre_placed.rpt"/>
  <File Type="ROUTE-METHODOLOGY-DRC-PB" Name="vivado_wrapper_methodology_drc_routed.pb"/>
  <File Type="ROUTE-DCP" Name="vivado_wrapper_routed.dcp"/>
  <File Type="ROUTE-BLACKBOX-DCP" Name="vivado_wrapper_routed_bb.dcp"/>
  <File Type="POSTPLACE-PWROPT-DCP" Name="vivado_wrapper_postplace_pwropt.dcp"/>
  <File Type="ROUTE-DRC" Name="vivado_wrapper_drc_routed.rpt"/>
  <File Type="ROUTE-METHODOLOGY-DRC" Name="vivado_wrapper_methodology_drc_routed.rpt"/>
  <File Type="PLACE-SIMILARITY" Name="vivado_wrapper_incremental_reuse_placed.rpt"/>
  <File Type="ROUTE-DRC-PB" Name="vivado_wrapper_drc_routed.pb"/>
  <File Type="ROUTE-STATUS-PB" Name="vivado_wrapper_route_status.pb"/>
  <File Type="ROUTE-TIMINGSUMMARY" Name="vivado_wrapper_timing_summary_routed.rpt"/>
  <File Type="BG-BIT" Name="vivado_wrapper.bit"/>
  <File Type="PHYSOPT-DCP" Name="vivado_wrapper_physopt.dcp"/>
  <File Type="ROUTE-PWR" Name="vivado_wrapper_power_routed.rpt"/>
  <File Type="ROUTE-STATUS" Name="vivado_wrapper_route_status.rpt"/>
  <File Type="ROUTE-PWR-RPX" Name="vivado_wrapper_power_routed.rpx"/>
  <File Type="PHYSOPT-DRC" Name="vivado_wrapper_drc_physopted.rpt"/>
  <File Type="ROUTE-PWR-SUM" Name="vivado_wrapper_power_summary_routed.pb"/>
  <File Type="PLACE-TIMING" Name="vivado_wrapper_timing_summary_placed.rpt"/>
  <File Type="OPT-HWDEF" Name="vivado_wrapper.hwdef"/>
  <File Type="INIT-TIMING" Name="vivado_wrapper_timing_summary_init.rpt"/>
  <File Type="OPT-DCP" Name="vivado_wrapper_opt.dcp"/>
  <File Type="BITSTR-RBT" Name="vivado_wrapper.rbt"/>
  <File Type="POSTROUTE-PHYSOPT-TIMING" Name="vivado_wrapper_timing_summary_postroute_physopted.rpt"/>
  <File Type="BG-BIN" Name="vivado_wrapper.bin"/>
  <File Type="ROUTE-SIMILARITY" Name="vivado_wrapper_incremental_reuse_routed.rpt"/>
  <File Type="BITSTR-MSK" Name="vivado_wrapper.msk"/>
  <File Type="ROUTE-CLK" Name="vivado_wrapper_clock_utilization_routed.rpt"/>
  <File Type="BITSTR-NKY" Name="vivado_wrapper.nky"/>
  <File Type="PLACE-DCP" Name="vivado_wrapper_placed.dcp"/>
  <File Type="BITSTR-BMM" Name="vivado_wrapper_bd.bmm"/>
  <File Type="PWROPT-DCP" Name="vivado_wrapper_pwropt.dcp"/>
  <File Type="POSTROUTE-PHYSOPT-BLACKBOX-DCP" Name="vivado_wrapper_postroute_physopt_bb.dcp"/>
  <File Type="WBT-USG" Name="usage_statistics_webtalk.html"/>
  <File Type="RDI-RDI" Name="vivado_wrapper.vdi"/>
  <File Type="PWROPT-TIMING" Name="vivado_wrapper_timing_summary_pwropted.rpt"/>
  <FileSet Name="sources" Type="DesignSrcs" RelSrcDir="$PSRCDIR/sources_1">
    <Filter Type="Srcs"/>
    <File Path="$PSRCDIR/sources_1/bd/vivado/vivado.bd">
      <FileInfo>
        <Attr Name="UsedIn" Val="synthesis"/>
        <Attr Name="UsedIn" Val="implementation"/>
        <Attr Name="UsedIn" Val="simulation"/>
      </FileInfo>
    </File>
    <File Path="$PSRCDIR/sources_1/bd/vivado/hdl/vivado_wrapper.v">
      <FileInfo>
        <Attr Name="UsedIn" Val="synthesis"/>
        <Attr Name="UsedIn" Val="implementation"/>
        <Attr Name="UsedIn" Val="simulation"/>
      </FileInfo>
    </File>
    <Config>
      <Option Name="DesignMode" Val="RTL"/>
      <Option Name="TopModule" Val="vivado_wrapper"/>
      <Option Name="TopAutoSet" Val="TRUE"/>
    </Config>
  </FileSet>
  <FileSet Name="constrs_in" Type="Constrs" RelSrcDir="$PSRCDIR/constrs_1">
    <Filter Type="Constrs"/>
    <Config>
      <Option Name="ConstrsType" Val="XDC"/>
    </Config>
  </FileSet>
  <Strategy Version="1" Minor="2">
    <StratHandle Name="Vivado Implementation Defaults" Flow="Vivado Implementation 2016"/>
    <Step Id="init_design"/>
    <Step Id="opt_design"/>
    <Step Id="power_opt_design"/>
    <Step Id="place_design"/>
    <Step Id="post_place_power_opt_design"/>
    <Step Id="phys_opt_design"/>
    <Step Id="route_design"/>
    <Step Id="post_route_phys_opt_design"/>
    <Step Id="write_bitstream"/>
  </Strategy>
</GenRun>
